{"assets":{"7E080253A1899680D20F5F4F2133EA3E":{"type":"texture","assetRequest":{"type":"slide","state":"incoming"},"url":"assets/7E080253A1899680D20F5F4F2133EA3E.svg","width":1024,"height":768},"F9A8C87C0F5DF6CFEFBF619F04EDEC65":{"type":"texture","assetRequest":{"type":"slide","state":"outgoing"},"url":"assets/F9A8C87C0F5DF6CFEFBF619F04EDEC65.svg","width":1024,"height":768}},"events":[{"effects":[{"beginTime":0,"baseLayer":{"animations":[],"initialState":{"affineTransform":[1,0,0,1,0,0],"masksToBounds":true,"rotation":0,"scale":1,"position":{"pointX":512,"pointY":384},"width":1024,"sublayerTransform":[1,0,0,0,0,1,0,0,0,0,1,0,0,0,0,1],"contentsRect":{"y":0,"x":0,"width":1,"height":1},"opacity":1,"edgeAntialiasingMask":0,"height":768,"hidden":false,"anchorPoint":{"pointX":0.5,"pointY":0.5}},"objectID":0,"layers":[{"animations":[],"initialState":{"affineTransform":[1,0,0,1,0,0],"masksToBounds":false,"rotation":0,"scale":1,"position":{"pointX":512,"pointY":384},"width":1024,"sublayerTransform":[1,0,0,0,0,1,0,0,0,0,1,-0.0004922987690640373,0,0,0,1],"contentsRect":{"y":0,"x":0,"width":1,"height":1},"opacity":1,"edgeAntialiasingMask":15,"height":768,"hidden":false,"anchorPoint":{"pointX":0.5,"pointY":0.5}},"layers":[{"animations":[],"layers":[],"initialState":{"affineTransform":[1,0,0,1,0,0],"masksToBounds":false,"rotation":0,"scale":1,"position":{"pointX":512,"pointY":384},"width":1024,"sublayerTransform":[1,0,0,0,0,1,0,0,0,0,1,0,0,0,0,1],"contentsRect":{"y":0,"x":0,"width":1,"height":1},"opacity":1,"edgeAntialiasingMask":0,"height":768,"hidden":false,"anchorPoint":{"pointX":0.5,"pointY":0.5}},"texture":"7E080253A1899680D20F5F4F2133EA3E"},{"animations":[{"from":{"scalar":false},"property":"hidden","beginTime":0,"to":{"scalar":true},"fillMode":"both","duration":0.01}],"layers":[],"initialState":{"affineTransform":[1,0,0,1,0,0],"masksToBounds":false,"rotation":0,"scale":1,"position":{"pointX":512,"pointY":384},"width":1024,"sublayerTransform":[1,0,0,0,0,1,0,0,0,0,1,0,0,0,0,1],"contentsRect":{"y":0,"x":0,"width":1,"height":1},"opacity":1,"edgeAntialiasingMask":0,"height":768,"hidden":false,"anchorPoint":{"pointX":0.5,"pointY":0.5}},"texture":"F9A8C87C0F5DF6CFEFBF619F04EDEC65"}]}]},"effects":[],"duration":0.01,"type":"transition","name":"none","objectID":0}],"automaticPlay":false,"hyperlinks":[],"accessibility":[{"text":"droppedImage.png","targetRectangle":{"y":362,"x":16,"width":546.0182505846024,"height":389.0000152587891}},{"text":"droppedImage.png","targetRectangle":{"y":362,"x":583.5,"width":422.0000004768372,"height":403.1533691883087}},{"text":"index.png","targetRectangle":{"y":9,"x":433,"width":158,"height":60}},{"text":"Collection of scripts and classes for image segmentation, geometric characterization and processing, mesh generation and post-processing for vascular modeling.","targetRectangle":{"y":158,"x":89,"width":900.421875,"height":63.21484375}},{"text":"Born as a result of post-doc time at Robarts Research Institute in 2003, continued through several years, with a few development bursts along the way.","targetRectangle":{"y":222,"x":89,"width":872.47265625,"height":63.21484375}},{"text":"Releasing code as open-source: forcing yourself to maintain a certain level of generality and overall quality. Beneficial, never been stolen to the point of being damaged. ","targetRectangle":{"y":286,"x":89,"width":936.515625,"height":55.21484375}},{"text":"The Vascular Modeling Toolkit (vmtk)","targetRectangle":{"y":90,"x":30.57470703125,"width":422.28515625,"height":27.21484375}}],"baseLayer":{"animations":[],"initialState":{"affineTransform":[1,0,0,1,0,0],"masksToBounds":true,"rotation":0,"scale":1,"position":{"pointX":512,"pointY":384},"width":1024,"sublayerTransform":[1,0,0,0,0,1,0,0,0,0,1,0,0,0,0,1],"contentsRect":{"y":0,"x":0,"width":1,"height":1},"opacity":1,"edgeAntialiasingMask":0,"height":768,"hidden":false,"anchorPoint":{"pointX":0.5,"pointY":0.5}},"objectID":0,"layers":[{"animations":[],"initialState":{"affineTransform":[1,0,0,1,0,0],"masksToBounds":false,"rotation":0,"scale":1,"position":{"pointX":512,"pointY":384},"width":1024,"sublayerTransform":[1,0,0,0,0,1,0,0,0,0,1,-0.0004922987690640373,0,0,0,1],"contentsRect":{"y":0,"x":0,"width":1,"height":1},"opacity":1,"edgeAntialiasingMask":15,"height":768,"hidden":false,"anchorPoint":{"pointX":0.5,"pointY":0.5}},"layers":[{"animations":[],"layers":[],"initialState":{"affineTransform":[1,0,0,1,0,0],"masksToBounds":false,"rotation":0,"scale":1,"position":{"pointX":512,"pointY":384},"width":1024,"sublayerTransform":[1,0,0,0,0,1,0,0,0,0,1,0,0,0,0,1],"contentsRect":{"y":0,"x":0,"width":1,"height":1},"opacity":1,"edgeAntialiasingMask":0,"height":768,"hidden":false,"anchorPoint":{"pointX":0.5,"pointY":0.5}},"texture":"7E080253A1899680D20F5F4F2133EA3E"},{"animations":[{"from":{"scalar":false},"property":"hidden","beginTime":0,"to":{"scalar":true},"fillMode":"both","duration":0.01}],"layers":[],"initialState":{"affineTransform":[1,0,0,1,0,0],"masksToBounds":false,"rotation":0,"scale":1,"position":{"pointX":512,"pointY":384},"width":1024,"sublayerTransform":[1,0,0,0,0,1,0,0,0,0,1,0,0,0,0,1],"contentsRect":{"y":0,"x":0,"width":1,"height":1},"opacity":1,"edgeAntialiasingMask":0,"height":768,"hidden":false,"anchorPoint":{"pointX":0.5,"pointY":0.5}},"texture":"F9A8C87C0F5DF6CFEFBF619F04EDEC65"}]}]}}]}